bgc_cloud/__init__.py
bgc_cloud/_fn.py
bgc_cloud/account.py
bgc_cloud/auth.py
bgc_cloud/controller.py
bgc_cloud/transport.py
bgc_cloud-1.0.8.dist-info/METADATA
bgc_cloud-1.0.8.dist-info/WHEEL
bgc_cloud-1.0.8.dist-info/top_level.txt
bgc_cloud-1.0.8.dist-info/RECORD
