Metadata-Version: 2.1
Name: bgc-cloud
Version: 1.0.8
Summary: BGC cloud helper
Home-page: https://github.com/Enrique-Mertoe/bgc_cloud
Author: Abuti Martin
Author-email: abutimartin778@gmail.com
Classifier: Programming Language :: Python :: 3
Classifier: License :: OSI Approved :: MIT License
Classifier: Operating System :: OS Independent
Requires-Python: >=3.6
Requires-Dist: requests
